SkillLink/SkillLink.py
SkillLink/__init__.py
SkillLink/SLLoader/Loader.py
SkillLink/SLLoader/__init__.py
SkillLink/SLPackageManager/PackageManager.py
SkillLink/SLPackageManager/__init__.py
SkillLink/SLParsers/Parsers.py
SkillLink/SLParsers/__init__.py
SkillLink/SLParsers/ActionParser/ActionParser.py
SkillLink/SLParsers/ActionParser/__init__.py
SkillLink/SLParsers/ArgumentParser/ArgumentParser.py
SkillLink/SLParsers/ArgumentParser/__init__.py
SkillLink/SLParsers/SkillParser/SkillParser.py
SkillLink/SLParsers/SkillParser/__init__.py
SkillLink/SLParsers/ToolParser/ToolParser.py
SkillLink/SLParsers/ToolParser/__init__.py
SkillLink/SLSkillMover/SkillMover.py
SkillLink/SLSkillMover/__init__.py
SkillLink/SLUtils/Utils.py
SkillLink/SLUtils/__init__.py
skilllink-0.2.8.dist-info/METADATA
skilllink-0.2.8.dist-info/WHEEL
skilllink-0.2.8.dist-info/top_level.txt
skilllink-0.2.8.dist-info/RECORD
